README
setup.py
instatrace/__init__.py
instatrace/commands.py
instatrace/control.py
instatrace/stats.py
instatrace.egg-info/PKG-INFO
instatrace.egg-info/SOURCES.txt
instatrace.egg-info/dependency_links.txt
instatrace.egg-info/entry_points.txt
instatrace.egg-info/requires.txt
instatrace.egg-info/top_level.txt