Metadata-Version: 1.0
Name: instatrace
Version: 1.0.1
Summary: Software statistics recorder/display
Home-page: http://wiki.github.com/pteichman/instatrace/
Author: Peter Teichman
Author-email: peter@teichman.org
License: UNKNOWN
Platform: UNKNOWN
Classifier: Development Status :: 5 - Production/Stable
Classifier: Environment :: Console
Classifier: Intended Audience :: Developers
Classifier: License :: OSI Approved :: MIT License
Classifier: Operating System :: OS Independent
Classifier: Programming Language :: Python
